AUTHORS
CHANGELOG.md
LICENSE
MANIFEST.in
README.md
avi2mkv.py
setup.py
avi2mkv.egg-info/PKG-INFO
avi2mkv.egg-info/SOURCES.txt
avi2mkv.egg-info/dependency_links.txt
avi2mkv.egg-info/entry_points.txt
avi2mkv.egg-info/pbr.json
avi2mkv.egg-info/top_level.txt