Metadata-Version: 1.1
Name: avi2mkv
Version: 1.1
Summary: Simple AVI to MKV converter
Home-page: http://github.com/igalarzab/avi2mkv
Author: Jose Ignacio Galarza
Author-email: igalarzab@gmail.com
License: MIT
Keywords: conversor,avi,mkv,simple
Platform: UNKNOWN
Classifier: Development Status :: 5 - Production/Stable
Classifier: Environment :: Console
Classifier: License :: OSI Approved :: MIT License
Classifier: Operating System :: OS Independent
Classifier: Programming Language :: Python :: 2
Classifier: Programming Language :: Python :: 3
Classifier: Topic :: Multimedia :: Sound/Audio :: Conversion
